DataClustering50YearsBeyondKmeansFanyi/README.md
DataClustering50YearsBeyondKmeansFanyi/__init__.py
DataClustering50YearsBeyondKmeansFanyi/__main__.py
DataClustering50YearsBeyondKmeansFanyi/file.pdf
DataClustering50YearsBeyondKmeansFanyi/index.html
data_clustering_50_years_beyond_kmeans_fanyi-2024.3.4.0.dist-info/METADATA
data_clustering_50_years_beyond_kmeans_fanyi-2024.3.4.0.dist-info/WHEEL
data_clustering_50_years_beyond_kmeans_fanyi-2024.3.4.0.dist-info/entry_points.txt
data_clustering_50_years_beyond_kmeans_fanyi-2024.3.4.0.dist-info/top_level.txt
data_clustering_50_years_beyond_kmeans_fanyi-2024.3.4.0.dist-info/RECORD
